chans/__init__.py
chans/__main__.py
chans/config.py
chans/data.py
chans/dependencies.py
chans/parser.py
chans/schemas.py
chans/server.py
chans/stream.py
chans/util.py
chans/chans/__init__.py
chans/chans/base.py
chans/chans/ch2.py
chans/chans/ch4.py
chans/static/favicon.ico
chans/static/css/base.css
chans/static/css/posts.css
chans/static/css/stream.css
chans/static/js/stream.js
chans/static/templates/base.j2
chans/static/templates/card.j2
chans/static/templates/posts.j2
chans/static/templates/settings.j2
chans/static/templates/stream.j2
chans-0.1.9.dist-info/METADATA
chans-0.1.9.dist-info/WHEEL
chans-0.1.9.dist-info/entry_points.txt
chans-0.1.9.dist-info/top_level.txt
chans-0.1.9.dist-info/RECORD
