Metadata-Version: 2.1
Name: chans
Version: 0.1.9
Summary: dag/task runner backed by sqlite
Author-email: Alexander Rodionov <tandav@tandav.me>
Project-URL: source, https://github.com/tandav/chans
Project-URL: homepage, https://chans.tandav.me
Requires-Python: >=3.10
Requires-Dist: uvicorn
Requires-Dist: fastapi
Requires-Dist: websockets
Requires-Dist: aiofiles
Requires-Dist: Jinja2
Requires-Dist: humanize
Requires-Dist: requests
Requires-Dist: redis[hiredis]
Requires-Dist: pipe21 (>=1.5.0)
Requires-Dist: tqdm
Requires-Dist: tenacity
Provides-Extra: dev
Requires-Dist: bumpver ; extra == 'dev'
Requires-Dist: pre-commit ; extra == 'dev'
Requires-Dist: pytest ; extra == 'dev'
